MANIFEST.in
README.md
setup.py
python_udptrack.egg-info/PKG-INFO
python_udptrack.egg-info/SOURCES.txt
python_udptrack.egg-info/dependency_links.txt
python_udptrack.egg-info/pbr.json
python_udptrack.egg-info/requires.txt
python_udptrack.egg-info/top_level.txt
udptrack/__init__.py
udptrack/exeception.py