Metadata-Version: 1.1
Name: python-udptrack
Version: 0.0.5
Summary: UNKNOWN
Home-page: https://github.com/plasmashadow/python-udptrack.git
Author: plasmashadow
Author-email: plasmashadowx@gmail.com
License: BSD License
Platform: UNKNOWN
Classifier: Programming Language :: Python
Classifier: Programming Language :: Python :: 2
Classifier: Intended Audience :: Developers
